{
  "recipes": [
    {
      "name": "泡菜炒饭",
      "picture": "./img/泡菜炒饭.jpg",
      "servings": "2", 
      "sections": [
        {
          "title": "材料",
          "items": [
            { "name": "培根", "amount": "60g，剪成小段" },
            { "name": "泡菜", "amount": "100g" },
            { "name": "米饭", "amount": "210G，隔夜饭/水米0.9比1" },
           
            { "name": "鸡蛋", "amount": "2个，炒散" },
            { "name": "紫菜", "amount": "少许，打碎" }
          ]
        },
        {
          "title": "酱料",
          "items": [
            { "name": "韩国辣椒粉", "amount": "7.5g" },
            { "name": "生抽", "amount": "7.5ml" },
            { "name": "耗油", "amount": "7.5g" },
            { "name": "糖", "amount": "3g" }
          ]
        }
      ],
      "steps": [
        {
          "description": "将酱汁和泡菜拌均匀"
        },
        {
          "description": "起锅热锅热油倒入鸡蛋液，略微凝固之后搅散，炒熟后倒出备用"
        },
        {
          "description": "重新起锅爆香培根和葱，加入泡菜酱汁炒香，加入饭和鸡蛋炒均匀"
        },
        {
          "description": "出锅，加碎紫菜",
          "picture": "./img/泡菜炒饭.jpg"
        }
      ]
    },






    {
      "name": "Bibimbap",
      "picture": "korean-tofu-soup.jpg",
      "sections": [
        {
          "title": "Ingredients",
          "items": [
            { "name": "Rice", "amount": "2 cups, cooked" },
            { "name": "Carrot", "amount": "1, julienned" },
            { "name": "Spinach", "amount": "1 cup, blanched" },
            { "name": "Zucchini", "amount": "1, thinly sliced" },
            { "name": "Egg", "amount": "4, fried" }
          ]
        }
      ],
      "steps": [
        {
          "description": "Prepare all ingredients and place them on top of the cooked rice in sections.",
          "picture": "/public/recipes/korean/steps/bibimbap/step1.png"
        },
        {
          "description": "Add a fried egg on top of each serving."
        },
        {
          "description": "Serve with a side of gochujang (Korean chili paste) and mix everything together before eating."
        }
      ]
    },
    {
      "name": "Tteokbokki",
      "picture": "korean-tofu-soup.jpg",
      "sections": [
        {
          "title": "Ingredients",
          "items": [
            { "name": "Rice Cakes", "amount": "2 cups" },
            { "name": "Fish Cake", "amount": "1 cup, sliced" },
            { "name": "Gochujang", "amount": "3 tablespoons" },
            { "name": "Sugar", "amount": "1 tablespoon" },
            { "name": "Green Onion", "amount": "1/4 cup, chopped" }
          ]
        }
      ],
      "steps": [
        {
          "description": "Boil the rice cakes until soft, then drain."
        },
        {
          "description": "In a pan, mix gochujang, sugar, and a bit of water to make the sauce."
        },
        {
          "description": "Add rice cakes and fish cake to the sauce, cooking until the sauce thickens."
        },
        {
          "description": "Garnish with green onions and serve hot."
        }
      ]
    },
    {
      "name": "Tteokbokki",
      "picture": "korean-tofu-soup.jpg",
      "sections": [
        {
          "title": "Ingredients",
          "items": [
            { "name": "Rice Cakes", "amount": "2 cups" },
            { "name": "Fish Cake", "amount": "1 cup, sliced" },
            { "name": "Gochujang", "amount": "3 tablespoons" },
            { "name": "Sugar", "amount": "1 tablespoon" },
            { "name": "Green Onion", "amount": "1/4 cup, chopped" }
          ]
        }
      ],
      "steps": [
        {
          "description": "Boil the rice cakes until soft, then drain."
        },
        {
          "description": "In a pan, mix gochujang, sugar, and a bit of water to make the sauce."
        },
        {
          "description": "Add rice cakes and fish cake to the sauce, cooking until the sauce thickens."
        },
        {
          "description": "Garnish with green onions and serve hot."
        }
      ]
    }

    
  ]
}
